{"type": "table", "namespace": "vodafone", "model": "SOURCE INTERFACE 02.05.000", "package": "SOURCE INTERFACE 02.05.000", "name": "ARTICLE", "code": "ARTICLE", "comment": "", "description": "Note", "source system [source]": "CCB", "prod env machine [location]": "shop4", "prod env directory [location]": "/dw4/urfmfs1/abinitio/mfs/mfs_4way/oev/COMMON/URF_CUR_DATA/main", "dml path [location]": "/edwsw/sandboxes/public_sand/common/main/VFDE/public/DWH_PUB/dml/source/ccb/ARTICLE.dml", "file name": "article.<yyyymmddhhmmss>.main.a.dat", "interface mode [update mode]": "Delta", "execution frequency [frequency]": "Daily", "file format - characterset": "ASCII", "header": "False", "footer": "False", "newline delimiter": "\\n", "number of files sent on daily basis": "1.000000", "records in daily file": "3292", "dbms model target": "Teradata V13", "row growth rate per year": 10.0, "initial rows": 0.0, "primary key": {"name": "Key_1", "columns": ["ARTICLE_VERSION_ID"]}, "mapping": [], "column": [{"name": "ARTICLE_VERSION_ID", "nullable": false, "db data type": "CHAR(16)", "conformed data type": "string", "fixed field length combined": 16, "fixed field length": 16, "format": "", "description": "", "comment": "Article Version Identifier", "primary": true, "foreign key": false, "transformation": null, "mapping": []}, {"name": "CHANGE_TYPE", "nullable": true, "db data type": "CHAR(1)", "conformed data type": "string", "fixed field length combined": 1, "fixed field length": 1, "format": "", "description": "", "comment": "Data warehouse entry last action type: \"I\"-Inserted, \"U\"-Updated, \"D\"-Deleted.", "primary": false, "foreign key": false, "transformation": null, "mapping": []}, {"name": "LOADTM", "nullable": true, "db data type": "TIMESTAMP", "conformed data type": "datetime", "fixed field length": 14, "fixed field length combined": 14, "format": "YYYYMMDDHH24MISS", "description": "", "comment": " - data warehouse entry change date timestamp (Original name in the DWHDB \"_LOADTM\")", "primary": false, "foreign key": false, "transformation": null, "mapping": []}, {"name": "ARTICLE_CODE", "nullable": true, "db data type": "CHAR(16)", "conformed data type": "string", "fixed field length combined": 16, "fixed field length": 16, "format": "", "description": "", "comment": "Code for Article to uniquely identify an Article", "primary": false, "foreign key": false, "transformation": null, "mapping": []}, {"name": "ARTICLE_NAME", "nullable": true, "db data type": "CHAR(60)", "conformed data type": "string", "fixed field length combined": 60, "fixed field length": 60, "format": "", "description": "", "comment": "Name of the Article", "primary": false, "foreign key": false, "transformation": null, "mapping": []}, {"name": "EFFECTIVE_DATE", "nullable": true, "db data type": "TIMESTAMP", "conformed data type": "datetime", "fixed field length": 14, "fixed field length combined": 14, "format": "YYYYMMDDHH24MISS", "description": "", "comment": "The Date from which the Effective Status is appliable to the Article Version", "primary": false, "foreign key": false, "transformation": null, "mapping": []}, {"name": "EFFECTIVE_STATUS", "nullable": true, "db data type": "CHAR(6)", "conformed data type": "string", "fixed field length combined": 6, "fixed field length": 6, "format": "", "description": "", "comment": "Effective Status of the Article version on Effective Date", "primary": false, "foreign key": false, "transformation": null, "mapping": []}, {"name": "DISCONTINUE_IND", "nullable": true, "db data type": "CHAR(1)", "conformed data type": "string", "fixed field length combined": 1, "fixed field length": 1, "format": "", "description": "", "comment": "Indicator to show if the Article is discontinued. A discontinued Article can not be associated with any other object", "primary": false, "foreign key": false, "transformation": null, "mapping": []}, {"name": "DESCRIPTIVE_TEXT", "nullable": true, "db data type": "CHAR(360)", "conformed data type": "string", "fixed field length combined": 360, "fixed field length": 360, "format": "", "description": "", "comment": "Detailed description of the Article", "primary": false, "foreign key": false, "transformation": null, "mapping": []}, {"name": "AUDIT_UPDATE_USER_ID", "nullable": true, "db data type": "CHAR(15)", "conformed data type": "string", "fixed field length combined": 15, "fixed field length": 15, "format": "", "description": "", "comment": "Audit information capturing user id of last update", "primary": false, "foreign key": false, "transformation": null, "mapping": []}, {"name": "AUDIT_UPDATE_DATE_TIME", "nullable": true, "db data type": "TIMESTAMP", "conformed data type": "datetime", "fixed field length": 14, "fixed field length combined": 14, "format": "YYYYMMDDHH24MISS", "description": "", "comment": "Audit information capturing date and time of last update", "primary": false, "foreign key": false, "transformation": null, "mapping": []}, {"name": "UPDATE_NUMBER", "nullable": true, "db data type": "DECIMAL(40)", "conformed data type": "float", "fixed field length combined": 40, "fixed field length": 40, "format": "", "description": "", "comment": "Version number of the row. The version number starts with a random number and is  incremented on each update.  Update and Delete operations verify that the number in the database is equal to the  number used in the SQL statement (optimistic locking).", "primary": false, "foreign key": false, "transformation": null, "mapping": []}, {"name": "MEASURE_UNIT", "nullable": true, "db data type": "DECIMAL(40)", "conformed data type": "float", "fixed field length combined": 40, "fixed field length": 40, "format": "", "description": "", "comment": "MeasureUnit of the Article", "primary": false, "foreign key": false, "transformation": null, "mapping": []}, {"name": "CO_PRODUCT", "nullable": true, "db data type": "DECIMAL(40)", "conformed data type": "float", "fixed field length combined": 40, "fixed field length": 40, "format": "", "description": "", "comment": "CO-Product (relevant for SAP) of the Article", "primary": false, "foreign key": false, "transformation": null, "mapping": []}, {"name": "SALES_COMPONENT_TYPE", "nullable": true, "db data type": "DECIMAL(40)", "conformed data type": "float", "fixed field length combined": 40, "fixed field length": 40, "format": "", "description": "", "comment": "Type to identify the component for sales (SAP)", "primary": false, "foreign key": false, "transformation": null, "mapping": []}, {"name": "SALES_SEGMENT", "nullable": true, "db data type": "DECIMAL(40)", "conformed data type": "float", "fixed field length combined": 40, "fixed field length": 40, "format": "", "description": "", "comment": "Identifier of segment group for sales (SAP)", "primary": false, "foreign key": false, "transformation": null, "mapping": []}, {"name": "NEWLINE", "nullable": true, "db data type": "CHAR(%n)", "conformed data type": "string", "fixed field length combined": "%n", "fixed field length": 0, "format": "", "description": "", "comment": "N/A", "primary": false, "foreign key": false, "transformation": null, "mapping": []}]}