{"type": "table", "namespace": "vodafone", "model": "SOURCE INTERFACE 02.05.000", "package": "SOURCE INTERFACE 02.05.000", "name": "TARIFF_OFFER_GRP_REL", "code": "TARIFF_OFFER_GRP_REL", "comment": "comment missing", "description": "", "ppm id": "PPM_402594_418261", "project code": "RDM_OTO", "file name": "RDM..TARIFF_OFFER_GRP_REL.YYYYMMDDHHMNSS.A901", "mode": "Full", "markets": "NA", "input file type mfs": "false", "newline delimiter": "\\n", "compressed file": "false", "characterset": "UTF8", "source file type": "Delimited", "delimiter": "^|^", "header": "false", "footer": "false", "number of files sent on daily basis": "1", "execution frequency": "Daily", "execution type": "Latest", "historization": "true", "historization type": "SCD2_SD", "date field driving historization": "TARIFF_EFFECTIVE_DATE", "duplicate handling": "false", "oto target": "ODS", "source comes from": "RDM", "archival cfm": "true", "archival sa": "true", "sandbox": "/opt/SP/edwsw/sandboxes/private_sand/ahazra2/main/VFDE/private/oto_load/rdm_oto/", "target table name": "TARIFF_OFFER_GRP_REL", "filename details": "", "prod env directory": "", "prod env machine": "", "extract type": "", "expected volume": "", "records full file": "", "records daily file": "", "job name": "", "schedule name": "", "header detail": "", "footer detail": "", "execution frequency details": "", "data retention": "", "ddl template": "true", "oto": "true", "file format definition": "CSV", "reference database name [database name] ": "ODS_RDM_T${EDWENV}", "source system [source]": "RDM", "dbms model target": "Teradata V13", "row growth rate per year": 10.0, "initial rows": 0.0, "primary key": {"name": "Key_1", "columns": ["RULESET_CD", "TARIFF_GROUP_ID"]}, "mapping": [], "column": [{"name": "RULESET_CD", "nullable": false, "db data type": "CHAR(5)", "conformed data type": "string", "fixed field length combined": 5, "fixed field length": 5, "format": "", "description": "", "comment": "Contains the id to distinguish between the different tariff hierarchies.", "primary": true, "foreign key": false, "transformation": null, "source_target_flag": "ST", "mapping": []}, {"name": "TARIFF_GROUP_ID", "nullable": false, "db data type": "CHAR(12)", "conformed data type": "string", "fixed field length combined": 12, "fixed field length": 12, "format": "", "description": "", "comment": "Containing the existing TARI id (e.g. TARI_6509)", "primary": true, "foreign key": false, "transformation": null, "source_target_flag": "ST", "mapping": []}, {"name": "RELATED_TARIFF_GROUP_ID", "nullable": true, "db data type": "CHAR(12)", "conformed data type": "string", "fixed field length combined": 12, "fixed field length": 12, "format": "", "description": "", "comment": "Containing the existing TARI id (e.g. TARI_6509)", "primary": false, "foreign key": false, "transformation": null, "source_target_flag": "ST", "mapping": []}, {"name": "TARIFF_EFFECTIVE_DATE", "nullable": true, "db data type": "DATE", "conformed data type": "date", "fixed field length": 8, "fixed field length combined": 8, "format": "YYYYMMDD", "description": "", "comment": "The Effective_date, when the Tariff Group Relation will be active (used for historicization in ODS_RDM_PRD)", "primary": false, "foreign key": false, "transformation": null, "source_target_flag": "ST", "mapping": []}]}